odoo/addons/ssi_financial_accounting_operating_unit/README.rst
odoo/addons/ssi_financial_accounting_operating_unit/__init__.py
odoo/addons/ssi_financial_accounting_operating_unit/__manifest__.py
odoo/addons/ssi_financial_accounting_operating_unit/models/__init__.py
odoo/addons/ssi_financial_accounting_operating_unit/models/account_bank_statement.py
odoo/addons/ssi_financial_accounting_operating_unit/models/account_bank_statement_line.py
odoo/addons/ssi_financial_accounting_operating_unit/models/account_journal.py
odoo/addons/ssi_financial_accounting_operating_unit/models/account_move.py
odoo/addons/ssi_financial_accounting_operating_unit/models/account_move_line.py
odoo/addons/ssi_financial_accounting_operating_unit/security/ir_rule/account_bank_statement.xml
odoo/addons/ssi_financial_accounting_operating_unit/security/ir_rule/account_journal.xml
odoo/addons/ssi_financial_accounting_operating_unit/security/ir_rule/account_move.xml
odoo/addons/ssi_financial_accounting_operating_unit/security/ir_rule/account_move_line.xml
odoo/addons/ssi_financial_accounting_operating_unit/static/description/icon.png
odoo/addons/ssi_financial_accounting_operating_unit/views/account_bank_statement_views.xml
odoo/addons/ssi_financial_accounting_operating_unit/views/account_journal_views.xml
odoo/addons/ssi_financial_accounting_operating_unit/views/account_move_line_views.xml
odoo/addons/ssi_financial_accounting_operating_unit/views/account_move_views.xml
odoo14_addon_ssi_financial_accounting_operating_unit-14.0.1.0.0.dist-info/METADATA
odoo14_addon_ssi_financial_accounting_operating_unit-14.0.1.0.0.dist-info/WHEEL
odoo14_addon_ssi_financial_accounting_operating_unit-14.0.1.0.0.dist-info/top_level.txt
odoo14_addon_ssi_financial_accounting_operating_unit-14.0.1.0.0.dist-info/RECORD
